quspin_vqa/__init__.py
quspin_vqa/utils.py
quspin_vqa/algo/__init__.py
quspin_vqa/algo/cvqite.py
quspin_vqa/algo/gqaoa.py
quspin_vqa/algo/qaoa.py
quspin_vqa/algo/variational_algorithm.py
quspin_vqa/algo/vqite.py
quspin_vqa/opt/__init__.py
quspin_vqa/opt/optimizer.py
quspin_vqa/opt/solver.py
quspin_vqa/phys/__init__.py
quspin_vqa/phys/ising.py
quspin_vqa/phys/physics_system.py
quspin_vqa-0.0.4.dist-info/LICENSE
quspin_vqa-0.0.4.dist-info/METADATA
quspin_vqa-0.0.4.dist-info/WHEEL
quspin_vqa-0.0.4.dist-info/top_level.txt
quspin_vqa-0.0.4.dist-info/RECORD
