Metadata-Version: 2.1
Name: quspin-vqa
Version: 0.0.4
Summary: Variatioanl Quantum Algorithms
Home-page: https://github.com/JiahaoYao/VQA
Author: Jimmy
Author-email: jiahaoyao.math@gmail.com
License: MIT
Keywords: quantum computing,variational quantum algorithms,quantum machine learning,Reinforcement Learning,Quspin
Classifier: Development Status :: 4 - Beta
Classifier: Intended Audience :: Developers
Classifier: Topic :: Scientific/Engineering :: Artificial Intelligence
Classifier: License :: OSI Approved :: MIT License
Classifier: Programming Language :: Python :: 3.6
License-File: LICENSE
